aiogram/__init__.py
aiogram/__meta__.py
aiogram/exceptions.py
aiogram/loggers.py
aiogram/py.typed
aiogram/client/__init__.py
aiogram/client/bot.py
aiogram/client/context_controller.py
aiogram/client/telegram.py
aiogram/client/session/__init__.py
aiogram/client/session/aiohttp.py
aiogram/client/session/base.py
aiogram/client/session/middlewares/__init__.py
aiogram/client/session/middlewares/base.py
aiogram/client/session/middlewares/manager.py
aiogram/client/session/middlewares/request_logging.py
aiogram/dispatcher/__init__.py
aiogram/dispatcher/dispatcher.py
aiogram/dispatcher/flags.py
aiogram/dispatcher/router.py
aiogram/dispatcher/event/__init__.py
aiogram/dispatcher/event/bases.py
aiogram/dispatcher/event/event.py
aiogram/dispatcher/event/handler.py
aiogram/dispatcher/event/telegram.py
aiogram/dispatcher/middlewares/__init__.py
aiogram/dispatcher/middlewares/base.py
aiogram/dispatcher/middlewares/error.py
aiogram/dispatcher/middlewares/manager.py
aiogram/dispatcher/middlewares/user_context.py
aiogram/enums/__init__.py
aiogram/enums/bot_command_scope_type.py
aiogram/enums/chat_action.py
aiogram/enums/chat_member_status.py
aiogram/enums/chat_type.py
aiogram/enums/content_type.py
aiogram/enums/currency.py
aiogram/enums/dice_emoji.py
aiogram/enums/encrypted_passport_element.py
aiogram/enums/inline_query_result_type.py
aiogram/enums/input_media_type.py
aiogram/enums/mask_position_point.py
aiogram/enums/menu_button_type.py
aiogram/enums/message_entity_type.py
aiogram/enums/parse_mode.py
aiogram/enums/passport_element_error_type.py
aiogram/enums/poll_type.py
aiogram/enums/sticker_format.py
aiogram/enums/sticker_type.py
aiogram/enums/topic_icon_color.py
aiogram/enums/update_type.py
aiogram/filters/__init__.py
aiogram/filters/base.py
aiogram/filters/callback_data.py
aiogram/filters/chat_member_updated.py
aiogram/filters/command.py
aiogram/filters/exception.py
aiogram/filters/logic.py
aiogram/filters/magic_data.py
aiogram/filters/state.py
aiogram/fsm/__init__.py
aiogram_dev3quest-3.0.0.dist-info/METADATA
aiogram_dev3quest-3.0.0.dist-info/WHEEL
aiogram_dev3quest-3.0.0.dist-info/licenses/LICENSE
aiogram_dev3quest-3.0.0.dist-info/RECORD
