Metadata-Version: 2.4
Name: aiogram-dev3quest
Version: 3.0.0
Summary: Modern and fully asynchronous framework for Telegram Bot API
Project-URL: Homepage, https://aiogram.dev/
Project-URL: Documentation, https://docs.aiogram.dev/
Project-URL: Repository, https://github.com/aiogram/aiogram/
Author-email: Alex Root Junior <jroot.junior@gmail.com>
Maintainer-email: Alex Root Junior <jroot.junior@gmail.com>
License-Expression: MIT
License-File: LICENSE
Keywords: api,asyncio,bot,framework,telegram,wrapper
Classifier: Development Status :: 5 - Production/Stable
Classifier: Environment :: Console
Classifier: Framework :: AsyncIO
Classifier: Intended Audience :: Developers
Classifier: Intended Audience :: System Administrators
Classifier: License :: OSI Approved :: MIT License
Classifier: Programming Language :: Python :: 3.9
Classifier: Programming Language :: Python :: 3.10
Classifier: Programming Language :: Python :: 3.11
Classifier: Programming Language :: Python :: 3.12
Classifier: Programming Language :: Python :: 3.13
Classifier: Programming Language :: Python :: Implementation :: PyPy
Classifier: Topic :: Communications :: Chat
Classifier: Topic :: Software Development :: Libraries :: Application Frameworks
Classifier: Topic :: Software Development :: Libraries :: Python Modules
Classifier: Typing :: Typed
Requires-Python: >=3.9
Requires-Dist: aiofiles<24.2,>=23.2.1
Requires-Dist: aiohttp<3.12,>=3.9.0
Requires-Dist: certifi>=2023.7.22
Requires-Dist: magic-filter<1.1,>=1.0.12
Requires-Dist: pydantic<2.12,>=2.4.1
Requires-Dist: typing-extensions<=5.0,>=4.7.0
Provides-Extra: cli
Requires-Dist: aiogram-cli<2.0.0,>=1.1.0; extra == 'cli'
Provides-Extra: dev
Requires-Dist: black~=24.4.2; extra == 'dev'
Requires-Dist: isort~=5.13.2; extra == 'dev'
Requires-Dist: motor-types~=1.0.0b4; extra == 'dev'
Requires-Dist: mypy~=1.10.0; extra == 'dev'
Requires-Dist: packaging~=24.1; extra == 'dev'
Requires-Dist: pre-commit~=3.5; extra == 'dev'
Requires-Dist: ruff~=0.5.1; extra == 'dev'
Requires-Dist: toml~=0.10.2; extra == 'dev'
Provides-Extra: docs
Requires-Dist: furo~=2024.8.6; extra == 'docs'
Requires-Dist: markdown-include~=0.8.1; extra == 'docs'
Requires-Dist: pygments~=2.18.0; extra == 'docs'
Requires-Dist: pymdown-extensions~=10.3; extra == 'docs'
Requires-Dist: sphinx-autobuild~=2024.9.3; extra == 'docs'
Requires-Dist: sphinx-copybutton~=0.5.2; extra == 'docs'
Requires-Dist: sphinx-intl~=2.2.0; extra == 'docs'
Requires-Dist: sphinx-substitution-extensions~=2024.8.6; extra == 'docs'
Requires-Dist: sphinxcontrib-towncrier~=0.4.0a0; extra == 'docs'
Requires-Dist: sphinx~=8.0.2; extra == 'docs'
Requires-Dist: towncrier~=24.8.0; extra == 'docs'
Provides-Extra: fast
Requires-Dist: aiodns>=3.0.0; extra == 'fast'
Requires-Dist: uvloop>=0.17.0; ((sys_platform == 'darwin' or sys_platform == 'linux') and platform_python_implementation != 'PyPy' and python_version < '3.13') and extra == 'fast'
Requires-Dist: uvloop>=0.21.0; ((sys_platform == 'darwin' or sys_platform == 'linux') and platform_python_implementation != 'PyPy' and python_version >= '3.13') and extra == 'fast'
Provides-Extra: i18n
Requires-Dist: babel~=2.13.0; extra == 'i18n'
Provides-Extra: mongo
Requires-Dist: motor<3.7.0,>=3.3.2; extra == 'mongo'
Provides-Extra: proxy
Requires-Dist: aiohttp-socks~=0.8.3; extra == 'proxy'
Provides-Extra: redis
Requires-Dist: redis[hiredis]<5.3.0,>=5.0.1; extra == 'redis'
Provides-Extra: test
Requires-Dist: aresponses~=2.1.6; extra == 'test'
Requires-Dist: pycryptodomex~=3.19.0; extra == 'test'
Requires-Dist: pytest-aiohttp~=1.0.5; extra == 'test'
Requires-Dist: pytest-asyncio~=0.21.1; extra == 'test'
Requires-Dist: pytest-cov~=4.1.0; extra == 'test'
Requires-Dist: pytest-html~=4.0.2; extra == 'test'
Requires-Dist: pytest-lazy-fixture~=0.6.3; extra == 'test'
Requires-Dist: pytest-mock~=3.12.0; extra == 'test'
Requires-Dist: pytest-mypy~=0.10.3; extra == 'test'
Requires-Dist: pytest~=7.4.2; extra == 'test'
Requires-Dist: pytz~=2023.3; extra == 'test'
